delphi/__init__.py
delphi/attack_steps.py
delphi/attacker.py
delphi/delphi.py
delphi/grad.py
delphi/oracle.py
delphi/trainer.py
delphi/cifar_models/__init__.py
delphi/cifar_models/resnet.py
delphi/cifar_models/vgg.py
delphi/distributions/__init__.py
delphi/distributions/censored_multivariate_normal.py
delphi/distributions/censored_normal.py
delphi/distributions/distributions.py
delphi/distributions/multivariate_normal.py
delphi/distributions/normal.py
delphi/distributions/truncated_boolean_product.py
delphi/distributions/truncated_multivariate_normal.py
delphi/distributions/truncated_normal.py
delphi/imagenet_models/__init__.py
delphi/imagenet_models/vgg.py
delphi/stats/__init__.py
delphi/stats/gumbel_ce.py
delphi/stats/lasso_regression.py
delphi/stats/linear_model.py
delphi/stats/linear_regression.py
delphi/stats/logistic_regression.py
delphi/stats/probit_regression.py
delphi/stats/softmax.py
delphi/stats/stats.py
delphi/stats/truncated_elastic_net_regression.py
delphi/stats/truncated_lasso_regression.py
delphi/stats/truncated_linear_regression.py
delphi/stats/truncated_logistic_regression.py
delphi/stats/truncated_probit_regression.py
delphi/stats/truncated_ridge_regression.py
delphi/utils/__init__.py
delphi/utils/constants.py
delphi/utils/data_augmentation.py
delphi/utils/datasets.py
delphi/utils/defaults.py
delphi/utils/folder.py
delphi/utils/helpers.py
delphi/utils/loaders.py
delphi/utils/model_utils.py
delphi.ai-0.2.2.0.dist-info/LICENSE
delphi.ai-0.2.2.0.dist-info/METADATA
delphi.ai-0.2.2.0.dist-info/WHEEL
delphi.ai-0.2.2.0.dist-info/top_level.txt
delphi.ai-0.2.2.0.dist-info/RECORD
