Metadata-Version: 2.1
Name: delphi.ai
Version: 0.2.2.0
Summary: Package for Robust Statistics
Home-page: https://github.com/pstefanou12/delphi
Author: Patroklos Stefanou
Author-email: patstefanou@gmail.com
License: MIT
Project-URL: Repository, https://github.com/pstefanou12/delphi
Platform: UNKNOWN
Classifier: Development Status :: 3 - Alpha
Classifier: Programming Language :: Python :: 3
Classifier: License :: OSI Approved :: MIT License
Classifier: Operating System :: OS Independent
Requires-Python: >=3.6
License-File: LICENSE
Requires-Dist: tqdm
Requires-Dist: grpcio
Requires-Dist: psutil
Requires-Dist: gitpython
Requires-Dist: py3nvml
Requires-Dist: cox
Requires-Dist: scikit-learn
Requires-Dist: seaborn
Requires-Dist: torch
Requires-Dist: torchvision
Requires-Dist: pandas
Requires-Dist: numpy
Requires-Dist: scipy
Requires-Dist: GPUtil
Requires-Dist: dill
Requires-Dist: tensorboardX
Requires-Dist: tables
Requires-Dist: matplotlib
Requires-Dist: orthnet
